gitlab_helper_mcp/__init__.py
gitlab_helper_mcp/__main__.py
gitlab_helper_mcp/config.py
gitlab_helper_mcp/models.py
gitlab_helper_mcp/server.py
gitlab_helper_mcp-0.1.3.dist-info/licenses/LICENSE
gitlab_helper_mcp-0.1.3.dist-info/METADATA
gitlab_helper_mcp-0.1.3.dist-info/WHEEL
gitlab_helper_mcp-0.1.3.dist-info/entry_points.txt
gitlab_helper_mcp-0.1.3.dist-info/top_level.txt
gitlab_helper_mcp-0.1.3.dist-info/RECORD
