Metadata-Version: 2.4
Name: gitlab-helper-mcp
Version: 0.1.3
Summary: A Model Context Protocol (MCP) server for GitLab integration
Author-email: philo-veritas <edison.gee.lan@gmail.com>
Maintainer-email: philo-veritas <edison.gee.lan@gmail.com>
License-Expression: MIT
Keywords: mcp,gitlab,claude,ai
Classifier: Development Status :: 3 - Alpha
Classifier: Intended Audience :: Developers
Classifier: Operating System :: OS Independent
Classifier: Programming Language :: Python :: 3
Classifier: Programming Language :: Python :: 3.12
Classifier: Topic :: Communications :: Chat
Classifier: Topic :: Software Development :: Libraries :: Python Modules
Requires-Python: >=3.12
License-File: LICENSE
Requires-Dist: mcp[cli]>=1.13.1
Requires-Dist: pydantic>=2.11.7
Requires-Dist: python-gitlab>=6.3.0
Dynamic: license-file
